{
  "namespace": "hoamcui:hud",

  "hotbar_left_content@elm.empty_panel": {
    "controls": [
      {
        "hotbar_left_stack@elm.stack": {
          "orientation": "horizontal",
          "size": [ "100%c", "100%cm" ],
          "offset": [-3, 22],
          "anchor_from": "bottom_right",
          "anchor_to": "bottom_right",
          "use_child_anchors": true,
          "$padding_size": [3, 3],
          "controls": [
            {
              "player_paperdoll@hoamcui:player_paperdoll.player_paperdoll": {
                // "anchor_from": "bottom_middle",
                // "anchor_to": "bottom_middle",
                "bindings": [
                  {
                    "binding_name": "#paper_doll_visible",
                    "binding_name_override": "#visible"
                  }
                ]
              }
            },
            {
              "padding@elm.padding": {}
            },
            {
              "utility_tools@hoamcui:utility_tools.utility_tools": {
                // "anchor_from": "bottom_middle",
                // "anchor_to": "bottom_middle"
              }
            }
          ]
        }
      }
    ]
  }
}
